translitera/LICENSE.txt
translitera/README.reSTful
translitera/__init__.py
translitera/kn2en.json
translitera/kn2la.json
translitera/translitera.py
translitera-0.2.0.dev1.dist-info/DESCRIPTION.rst
translitera-0.2.0.dev1.dist-info/METADATA
translitera-0.2.0.dev1.dist-info/RECORD
translitera-0.2.0.dev1.dist-info/WHEEL
translitera-0.2.0.dev1.dist-info/entry_points.txt
translitera-0.2.0.dev1.dist-info/metadata.json
translitera-0.2.0.dev1.dist-info/top_level.txt
