Metadata-Version: 2.0
Name: translitera
Version: 0.2.0.dev1
Summary: Phonetic transliteration of text in Kannaḍa script into Latin/English characters
Home-page: https://github.com/sria91/translitera
Author: Srikanth Anantharam
Author-email: saprao@linux.com
License: Apache Software License
Download-URL: https://github.com/sria91/translitera
Keywords: translitera
Platform: UNKNOWN
Classifier: Development Status :: 2 - Pre-Alpha
Classifier: License :: OSI Approved :: Apache Software License
Classifier: Programming Language :: Python :: 3.5
